fds/__init__.py
fds/sdk/__init__.py
fds/sdk/ExchangeDataFeedSnapshotAPISymbolList/__init__.py
fds/sdk/ExchangeDataFeedSnapshotAPISymbolList/api_client.py
fds/sdk/ExchangeDataFeedSnapshotAPISymbolList/configuration.py
fds/sdk/ExchangeDataFeedSnapshotAPISymbolList/exceptions.py
fds/sdk/ExchangeDataFeedSnapshotAPISymbolList/model_utils.py
fds/sdk/ExchangeDataFeedSnapshotAPISymbolList/rest.py
fds/sdk/ExchangeDataFeedSnapshotAPISymbolList/api/__init__.py
fds/sdk/ExchangeDataFeedSnapshotAPISymbolList/api/snapshot_api.py
fds/sdk/ExchangeDataFeedSnapshotAPISymbolList/apis/__init__.py
fds/sdk/ExchangeDataFeedSnapshotAPISymbolList/model/__init__.py
fds/sdk/ExchangeDataFeedSnapshotAPISymbolList/model/df_snapshot_response.py
fds/sdk/ExchangeDataFeedSnapshotAPISymbolList/model/error_response.py
fds/sdk/ExchangeDataFeedSnapshotAPISymbolList/model/error_response_sub_errors.py
fds/sdk/ExchangeDataFeedSnapshotAPISymbolList/model/fields.py
fds/sdk/ExchangeDataFeedSnapshotAPISymbolList/model/specialfield.py
fds/sdk/ExchangeDataFeedSnapshotAPISymbolList/models/__init__.py
fds.sdk.ExchangeDataFeedSnapshotAPISymbolList-0.21.15.dist-info/LICENSE
fds.sdk.ExchangeDataFeedSnapshotAPISymbolList-0.21.15.dist-info/METADATA
fds.sdk.ExchangeDataFeedSnapshotAPISymbolList-0.21.15.dist-info/WHEEL
fds.sdk.ExchangeDataFeedSnapshotAPISymbolList-0.21.15.dist-info/top_level.txt
fds.sdk.ExchangeDataFeedSnapshotAPISymbolList-0.21.15.dist-info/RECORD
